skzeros/_AAA.py
skzeros/__init__.py
skzeros/_domain.py
skzeros/_integrate.py
skzeros/_version.py
skzeros/_zeros.py
skzeros-0.0.2.dist-info/METADATA
skzeros-0.0.2.dist-info/WHEEL
skzeros-0.0.2.dist-info/licenses/LICENSE
skzeros-0.0.2.dist-info/RECORD
