Metadata-Version: 2.4
Name: skzeros
Version: 0.0.2
Summary: A package to compute all the poles and zeros of a holomorphic function in a region of the complex plane.
Project-URL: Homepage, https://github.com/j-bowhay/scikit-zeros
Project-URL: Bug Tracker, https://github.com/j-bowhay/scikit-zeros/issues
Project-URL: Discussions, https://github.com/j-bowhay/scikit-zeros/discussions
Project-URL: Changelog, https://github.com/j-bowhay/scikit-zeros/releases
Author-email: Jake Bowhay <jb9.bowhay@gmail.com>
License-File: LICENSE
Classifier: Development Status :: 1 - Planning
Classifier: Intended Audience :: Developers
Classifier: Intended Audience :: Science/Research
Classifier: License :: OSI Approved :: MIT License
Classifier: Operating System :: OS Independent
Classifier: Programming Language :: Python
Classifier: Programming Language :: Python :: 3
Classifier: Programming Language :: Python :: 3 :: Only
Classifier: Programming Language :: Python :: 3.10
Classifier: Programming Language :: Python :: 3.11
Classifier: Programming Language :: Python :: 3.12
Classifier: Programming Language :: Python :: 3.13
Classifier: Topic :: Scientific/Engineering
Classifier: Typing :: Typed
Requires-Python: >=3.10
Requires-Dist: matplotlib
Requires-Dist: numpy>=2
Requires-Dist: scipy>=1.15
Provides-Extra: dev
Requires-Dist: pytest-cov>=3; extra == 'dev'
Requires-Dist: pytest>=6; extra == 'dev'
Requires-Dist: scipy-stubs; extra == 'dev'
Provides-Extra: docs
Requires-Dist: furo>=2023.08.17; extra == 'docs'
Requires-Dist: myst-parser>=0.13; extra == 'docs'
Requires-Dist: sphinx-autodoc-typehints; extra == 'docs'
Requires-Dist: sphinx-copybutton; extra == 'docs'
Requires-Dist: sphinx>=7.0; extra == 'docs'
Provides-Extra: test
Requires-Dist: pytest-cov>=3; extra == 'test'
Requires-Dist: pytest>=6; extra == 'test'
